ihcsdk/__init__.py
ihcsdk/ihcclient.py
ihcsdk/ihcconnection.py
ihcsdk/ihccontroller.py
ihcsdk/ihcsslconnection.py
ihcsdk/certs/ihc.crt
ihcsdk/certs/ihc3.crt
ihcsdk-2.8.10.dist-info/METADATA
ihcsdk-2.8.10.dist-info/WHEEL
ihcsdk-2.8.10.dist-info/license.txt
ihcsdk-2.8.10.dist-info/top_level.txt
ihcsdk-2.8.10.dist-info/RECORD
