Metadata-Version: 2.2
Name: ihcsdk
Version: 2.8.10
Summary: IHC Python SDK
Home-page: https://github.com/dingusdk/PythonIhcSdk
Author: Jens Nielsen
License: GPL-3.0
License-File: license.txt
Requires-Dist: requests
Requires-Dist: cryptography
Dynamic: author
Dynamic: description
Dynamic: home-page
Dynamic: license
Dynamic: requires-dist
Dynamic: summary
